karrio/server/VERSION
karrio/server/__init__.py
karrio/server/__main__.py
karrio/server/asgi.py
karrio/server/workers.py
karrio/server/wsgi.py
karrio/server/lib/otel_huey.py
karrio/server/settings/__init__.py
karrio/server/settings/apm.py
karrio/server/settings/base.py
karrio/server/settings/cache.py
karrio/server/settings/constance.py
karrio/server/settings/debug.py
karrio/server/settings/email.py
karrio/server/settings/workers.py
karrio/server/static/extra/branding/android-chrome-192x192.png
karrio/server/static/extra/branding/android-chrome-512x512.png
karrio/server/static/extra/branding/favicon-16x16.png
karrio/server/static/extra/branding/favicon-32x32.png
karrio/server/static/extra/branding/favicon.ico
karrio/server/static/extra/branding/favicon.svg
karrio/server/static/extra/branding/icon-inverted.svg
karrio/server/static/extra/branding/icon.png
karrio/server/static/extra/branding/icon.svg
karrio/server/static/extra/branding/logo-inverted.svg
karrio/server/static/extra/branding/logo.svg
karrio/server/static/extra/branding/manifest.json
karrio/server/static/karrio/carriers/aramex_icon.svg
karrio/server/static/karrio/carriers/aramex_logo.svg
karrio/server/static/karrio/carriers/australiapost_icon.svg
karrio/server/static/karrio/carriers/australiapost_logo.svg
karrio/server/static/karrio/carriers/canadapost_icon.svg
karrio/server/static/karrio/carriers/canadapost_logo.svg
karrio/server/static/karrio/carriers/canpar_icon.svg
karrio/server/static/karrio/carriers/canpar_logo.svg
karrio/server/static/karrio/carriers/dhl_express_icon.svg
karrio/server/static/karrio/carriers/dhl_express_logo.svg
karrio/server/static/karrio/carriers/dhl_universal_icon.svg
karrio/server/static/karrio/carriers/dhl_universal_logo.svg
karrio/server/static/karrio/carriers/dicom_icon.svg
karrio/server/static/karrio/carriers/dicom_logo.svg
karrio/server/static/karrio/carriers/eshipper_logo.svg
karrio/server/static/karrio/carriers/fedex_icon.svg
karrio_server-2026.1.4.dist-info/METADATA
karrio_server-2026.1.4.dist-info/WHEEL
karrio_server-2026.1.4.dist-info/entry_points.txt
karrio_server-2026.1.4.dist-info/top_level.txt
karrio_server-2026.1.4.dist-info/RECORD
