Metadata-Version: 2.4
Name: karrio_server
Version: 2026.1.4
Summary: Multi-carrier shipping API
Author-email: karrio <hello@karrio.io>
License-Expression: Apache-2.0
Project-URL: Homepage, https://github.com/karrioapi/karrio-server
Classifier: Programming Language :: Python :: 3
Requires-Python: >=3.7
Requires-Dist: django
Requires-Dist: djangorestframework
Requires-Dist: djangorestframework-simplejwt
Requires-Dist: django-constance
Requires-Dist: django-filter
Requires-Dist: django-picklefield
Requires-Dist: django-email-verification
Requires-Dist: django-cors-headers
Requires-Dist: django-redis
Requires-Dist: django-two-factor-auth
Requires-Dist: django-oauth-toolkit
Requires-Dist: drf-api-tracking
Requires-Dist: drf-spectacular
Requires-Dist: dj-database-url
Requires-Dist: gunicorn
Requires-Dist: hiredis
Requires-Dist: uvicorn
Requires-Dist: jsonfield
Requires-Dist: more-itertools
Requires-Dist: requests
Requires-Dist: posthog
Requires-Dist: python-decouple
Requires-Dist: karrio_server_core
Requires-Dist: sentry-sdk
Requires-Dist: whitenoise
Requires-Dist: opentelemetry-instrumentation-django
Requires-Dist: opentelemetry-api
Requires-Dist: opentelemetry-sdk
Requires-Dist: opentelemetry-exporter-otlp
Requires-Dist: opentelemetry-instrumentation-requests
Requires-Dist: opentelemetry-instrumentation-logging
Requires-Dist: opentelemetry-instrumentation-psycopg2
Requires-Dist: opentelemetry-instrumentation-redis
Requires-Dist: opentelemetry-semantic-conventions
Requires-Dist: loguru
